nextcord/__init__.py
nextcord/__main__.py
nextcord/abc.py
nextcord/activity.py
nextcord/appinfo.py
nextcord/asset.py
nextcord/audit_logs.py
nextcord/backoff.py
nextcord/channel.py
nextcord/client.py
nextcord/colour.py
nextcord/components.py
nextcord/context_managers.py
nextcord/embeds.py
nextcord/emoji.py
nextcord/enums.py
nextcord/errors.py
nextcord/file.py
nextcord/flags.py
nextcord/gateway.py
nextcord/guild.py
nextcord/health_check.py
nextcord/http.py
nextcord/integrations.py
nextcord/interactions.py
nextcord/invite.py
nextcord/iterators.py
nextcord/member.py
nextcord/mentions.py
nextcord/message.py
nextcord/mixins.py
nextcord/object.py
nextcord/oggparse.py
nextcord/opus.py
nextcord/partial_emoji.py
nextcord/permissions.py
nextcord/player.py
nextcord/raw_models.py
nextcord/reaction.py
nextcord/role.py
nextcord/shard.py
nextcord/stage_instance.py
nextcord/state.py
nextcord/sticker.py
nextcord/team.py
nextcord/template.py
nextcord/threads.py
nextcord/user.py
nextcord/utils.py
nextcord/voice_client.py
nextcord/welcome_screen.py
nextcord/widget.py
nextcord/bin/libopus-0.x64.dll
nextcord/bin/libopus-0.x86.dll
nextcord/ext/commands/__init__.py
nextcord/ext/commands/_types.py
nextcord/ext/commands/bot.py
nextcord/ext/commands/cog.py
nextcord/ext/commands/context.py
nextcord/ext/commands/converter.py
nextcord/ext/commands/cooldowns.py
nextcord/ext/commands/core.py
nextcord/ext/commands/errors.py
nextcord/ext/commands/flags.py
nextcord/ext/commands/help.py
nextcord/ext/commands/view.py
nextcord/ext/tasks/__init__.py
nextcord/types/__init__.py
nextcord/types/activity.py
nextcord/types/appinfo.py
nextcord/types/audit_log.py
nextcord/types/channel.py
nextcord/types/components.py
nextcord/types/embed.py
nextcord/types/emoji.py
nextcord/types/gateway.py
nextcord/types/guild.py
nextcord/types/integration.py
nextcord/types/interactions.py
nextcord/types/invite.py
nextcord/types/member.py
nextcord/types/message.py
nextcord/types/raw_models.py
nextcord/types/role.py
nextcord_unaliased-2.0.0a2.dist-info/LICENSE
nextcord_unaliased-2.0.0a2.dist-info/METADATA
nextcord_unaliased-2.0.0a2.dist-info/WHEEL
nextcord_unaliased-2.0.0a2.dist-info/top_level.txt
nextcord_unaliased-2.0.0a2.dist-info/RECORD
