Metadata-Version: 2.1
Name: nextcord-unaliased
Version: 2.0.0a2
Summary: A Python wrapper for the Discord API forked from discord.py without the discord alias
Home-page: https://github.com/veni-vidi-code/nextcord/tree/withoutalias
Author: tag-epic & Rapptz
License: MIT
Project-URL: Original Repository, https://github.com/nextcord/nextcord
Project-URL: Original Package, https://pypi.org/project/nextcord/
Project-URL: Documentation, https://nextcord.readthedocs.io/en/latest/
Project-URL: Issue tracker, https://github.com/nextcord/nextcord/issues
Platform: UNKNOWN
Classifier: Development Status :: 5 - Production/Stable
Classifier: License :: OSI Approved :: MIT License
Classifier: Intended Audience :: Developers
Classifier: Natural Language :: English
Classifier: Operating System :: OS Independent
Classifier: Programming Language :: Python :: 3.8
Classifier: Programming Language :: Python :: 3.9
Classifier: Topic :: Internet
Classifier: Topic :: Software Development :: Libraries
Classifier: Topic :: Software Development :: Libraries :: Python Modules
Classifier: Topic :: Utilities
Classifier: Typing :: Typed
Requires-Python: >=3.8.0
License-File: LICENSE
Requires-Dist: aiohttp (<3.8.0,>=3.6.0)
Provides-Extra: docs
Requires-Dist: sphinx (==4.0.2) ; extra == 'docs'
Requires-Dist: sphinxcontrib-trio (==1.1.2) ; extra == 'docs'
Requires-Dist: sphinxcontrib-websupport ; extra == 'docs'
Provides-Extra: speed
Requires-Dist: orjson (>=3.5.4) ; extra == 'speed'
Requires-Dist: aiodns (>=1.1) ; extra == 'speed'
Requires-Dist: Brotli ; extra == 'speed'
Requires-Dist: cchardet ; extra == 'speed'
Provides-Extra: voice
Requires-Dist: PyNaCl (<1.5,>=1.3.0) ; extra == 'voice'
